{
 
  "1073066789": {
    "Name": "Singularity Assoc.",
    "Health": 75000,
    "MaxAbilities": 10,
    "Itens": [
      { "Nome": "Pisao" },
      { "Nome": "Ice Paradise" },
      { "Nome": "Flashstep" },
      { "Nome": "Supernova" },
      { "Nome": "The Real Esfere" },
      { "Nome": "Overdrive" },
      { "Nome": "DemonBash" },
      { "Nome": "DoubleJump", "Ignore": "true", "Attributes": { "Height": 120 } }
    ]
  },

  "34390641": {
    "Name": "Hueco Mundo",
    "Health": 35000,
    "Itens": [
      { "Nome": "Kokusen" },
      { "Nome": "ChuteDeFogo" },
      { "Nome": "Rasteira" },
      { "Nome": "Susanoo Skeleton" },
      { "Nome": "ChuteCongelante" },
      { "Nome": "Hadou" },
      { "Nome": "Lanza del Relámpago" },
      { "Nome": "Rinnegan", "Attributes": { "Range": 55 } },
      { "Nome": "Raio" }
    ]
  },
 
  "147416291": {
    "Name": "1337 | Society",
    "Health": 5000,
    "Itens": [
      { "Nome": "Kokusen" },
      { "Nome": "ChuteDeFogo" }

    ],
    "Colors": {
      "Nome": { "Texto": [169,169,169], "Borda": [0, 0, 0] },
      "Patente": { "Texto": [169,169,169], "Borda": [0, 0, 0] },
      "Team": { "Texto": [169,169,169], "Borda": [0, 0, 0] }
    }
  },

  "851244261": {
    "Name": "Os Ditadores",
    "Health": 5000,
    "Itens": [
      { "Nome": "Kokusen" },
      { "Nome": "ChuteDeFogo" }

    ],
    "Colors": {
      "Nome": { "Texto": [90, 0, 120], "Borda": [0, 0, 0] },
      "Patente": { "Texto": [90, 0, 120], "Borda": [0, 0, 0] },
      "Team": { "Texto": [90, 0, 120], "Borda": [0, 0, 0] }
    }
  },

    "34894857": {
    "Name": "NoCraK",
    "Health": 5000,
    "Itens": [
      { "Nome": "Kokusen" },
      { "Nome": "ChuteCongelante" }

    ],
    "Colors": {
      "Nome": { "Texto": [0, 0, 0], "Borda": [255, 255, 255] },
      "Patente": { "Texto": [0, 0, 0], "Borda": [255, 255, 255] },
      "Team": { "Texto": [100, 0, 0], "Borda": [0, 0, 0] }
    }
  },

    "34356664": {
    "Name": "Grécia antiga",
    "Health": 5000,
    "Itens": [
      { "Nome": "Kokusen" },
      { "Nome": "Raio" }

    ],
    "Colors": {
      "Nome": { "Texto": [100, 0, 0], "Borda": [0, 0, 0] },
      "Patente": { "Texto": [100, 0, 0], "Borda": [0, 0, 0] },
      "Team": { "Texto": [100, 0, 0], "Borda": [0, 0, 0] }
    }
  },




  "33656216": {
    "Name": "Blake Association",
    "Health": 5000,
    "Itens": [
      { "Nome": "Kokusen" },
      { "Nome": "ChuteDeFogo" },
      { "Nome": "Rasteira" },
      { "Nome": "SusanooEspada" },
      { "Nome": "ChuteCongelante" },
      { "Nome": "Rinnegan", "Attributes": { "Range": 55 } },
      { "Nome": "Raio" }
    ],
    "Colors": {
      "Nome": { "Texto": [255, 255, 255], "Borda": [232, 99, 255] },
      "Patente": { "Texto": [255, 255, 255], "Borda": [232, 99, 255] },
      "Team": { "Texto": [255, 255, 255], "Borda": [232, 99, 255] }
    }
  },

  "33963874": {
    "Name": "Eternity Order",
    "Health": 1000,
    "Itens": [
      { "Nome": "Kokusen" },
      { "Nome": "ChuteDeFogo" },
      { "Nome": "Rasteira" },
      { "Nome": "HakiDoRei" },
      { "Nome": "ChuteCongelante" },
      { "Nome": "Raio" }
    ],
    "Colors": {
      "Nome": { "Texto": [0, 0, 0], "Borda": [227, 196, 255] },
      "Patente": { "Texto": [0, 0, 0], "Borda": [227, 196, 255] },
      "Team": { "Texto": [0, 0, 0], "Borda": [227, 196, 255] }
    }
  },

  "32325896": {
    "Name": "Tokyo Manji Gang",
    "Health": 10000,
    "Itens": [
      { "Nome": "Kokusen" },
      { "Nome": "ChuteDeFogo" },
      { "Nome": "Rasteira" },
      { "Nome": "SusanooEspada" },
      { "Nome": "ChuteCongelante" },
      { "Nome": "Rinnegan", "Attributes": { "Range": 55 } },
      { "Nome": "Raio" }
    ],
    "Colors": {
      "Nome": { "Texto": [0, 0, 0], "Borda": [255, 255, 255] },
      "Patente": { "Texto": [0, 0, 0], "Borda": [255, 255, 255] },
      "Team": { "Texto": [0, 0, 0], "Borda": [255, 255, 0] }
    }
  },

  "515674220": {
    "Name": "Máfia da Passione",
    "Health": 10000,
    "Itens": [
      { "Nome": "Kokusen" },
      { "Nome": "ChuteDeFogo" },
      { "Nome": "Rasteira" },
      { "Nome": "SusanooEspada" },
      { "Nome": "ChuteCongelante" },
      { "Nome": "Rinnegan" },
      { "Nome": "Raio" }
    ],
    "Colors": {
      "Nome": { "Texto": [0, 0, 0], "Borda": [255, 255, 255] },
      "Patente": { "Texto": [255, 255, 255], "Borda": [0, 0, 0] },
      "Team": { "Texto": [255, 255, 255], "Borda": [0, 0, 0] }
    }
  },
  
  "944451740": {
    "Name": "Clã Uchiha",
    "Health": 10000,
    "Itens": [
      { "Nome": "Kokusen" },
      { "Nome": "ChuteDeFogo" },
      { "Nome": "Rasteira" },
      { "Nome": "SusanooEspada" },
      { "Nome": "Rinnegan" },
      { "Nome": "Raio" },
      { "Nome": "Sharingan" }
    ],
    "Colors": {
      "Nome": { "Texto": [255, 255, 255], "Borda": [0, 0, 0] },
      "Patente": { "Texto": [255, 255, 255], "Borda": [0, 0, 0] },
      "Team": { "Texto": [255, 255, 255], "Borda": [0, 0, 0] }
    }
  },

 "35716048": {
    "Name": "Império Obscuro",
    "Health": 1000,
    "Itens": [
      { "Nome": "Kokusen" },
      { "Nome": "ChuteDeFogo" },
      { "Nome": "Rasteira" },
      { "Nome": "Susanoo" },
      { "Nome": "Rinnegan" },
      { "Nome": "Raio" }
    ],
    "Colors": {
      "Nome": { "Texto": [201, 162, 39], "Borda": [0, 0, 0] },
      "Patente": { "Texto": [106, 13, 173], "Borda": [46, 26, 71] },
      "Team": { "Texto": [176, 141, 87], "Borda": [26, 16, 37] }
    }
  },

 "8046391": {
    "Name": "༒︎ 3 Divindades ༒︎",
    "Health": 1000,
    "Itens": [
      { "Nome": "Kokusen" },
      { "Nome": "ChuteDeFogo" },
      { "Nome": "Rasteira" },
      { "Nome": "Susanoo" },
      { "Nome": "Rinnegan" },
      { "Nome": "Raio" }
    ],
    "Colors": {
      "Nome": { "Texto": [0, 0, 0], "Borda": [255, 0, 0] },
      "Patente": { "Texto": [245, 233, 0], "Borda": [255, 0, 0] },
      "Team": { "Texto": [245, 233, 0], "Borda": [0, 0, 0] }
    }
  },

 "537506790": {
    "Name": "Invencibles",
    "Health": 1000,
    "Itens": [
      { "Nome": "Kokusen" },
      { "Nome": "ChuteDeFogo" },
      { "Nome": "Rasteira" },
      { "Nome": "Susanoo" },
      { "Nome": "Rinnegan" },
      { "Nome": "Raio" }
    ],
    "Colors": {
      "Nome": { "Texto": [153, 28, 255], "Borda": [0, 0, 0] },
      "Patente": { "Texto": [0, 0, 0], "Borda": [255, 255, 255] },
      "Team": { "Texto": [255, 255, 255], "Borda": [193, 117, 255] }
    }
  },

 "829692947": {
    "Name": "Solo Leveling Gang",
    "Health": 1000,
    "Itens": [
      { "Nome": "Kokusen" },
      { "Nome": "ChuteDeFogo" },
      { "Nome": "Rasteira" },
      { "Nome": "Susanoo" },
      { "Nome": "Rinnegan" },
      { "Nome": "Raio" }
    ],
    "Colors": {
      "Nome": { "Texto": [84, 0, 153], "Borda": [0, 0, 0] },
      "Patente": { "Texto": [84, 0, 153], "Borda": [0, 0, 0] },
      "Team": { "Texto": [84, 0, 153], "Borda": [0, 0, 0] }
    }
  },

 "33524892": {
    "Name": "Psikolera",
    "Health": 1000,
    "Itens": [
      { "Nome": "Kokusen" },
      { "Nome": "ChuteDeFogo" },
      { "Nome": "Rasteira" },
      { "Nome": "Susanoo" },
      { "Nome": "Rinnegan" },
      { "Nome": "Raio" }
    ],
    "Colors": {
      "Nome": { "Texto": [255, 0, 21], "Borda": [0, 0, 0] },
      "Patente": { "Texto": [255, 0, 21], "Borda": [0, 0, 0] },
      "Team": { "Texto": [255, 0, 21], "Borda": [0, 0, 0] }
    }
  },

  "34792528": {
    "Name": "Bleach Of Shinigami",
    "Health": 1000,
    "Itens": [
      { "Nome": "Kokusen" },
      { "Nome": "ChuteDeFogo" },
      { "Nome": "Rasteira" },
      { "Nome": "Susanoo" },
      { "Nome": "Rinnegan" },
      { "Nome": "Raio" },
      { "Nome": "Susanoo Skeleton" }
    ],
    "Colors": {
      "Nome": { "Texto": [0, 0, 0], "Borda": [255, 102, 242] },
      "Patente": { "Texto": [0, 0, 0], "Borda": [255, 102, 242] },
      "Team": { "Texto": [0, 0, 0], "Borda": [255, 102, 242] }
    }
  },

  "32419373": {
    "Name": "龍 ✦ Super Novas ✦ 龍",
    "Health": 1000,
    "Itens": [
      { "Nome": "Kokusen" },
      { "Nome": "ChuteDeFogo" },
      { "Nome": "Rasteira" },
      { "Nome": "Susanoo" },
      { "Nome": "Rinnegan" },
      { "Nome": "Raio" }
    ],
    "Colors": {
      "Nome": { "Texto": [255, 255, 255], "Borda": [255, 20, 235] },
      "Patente": { "Texto": [255, 255, 255], "Borda": [255, 20, 235] },
      "Team": { "Texto": [255, 255, 255], "Borda": [255, 20, 235] }
    }
  },

  "35338244": {
    "Name": "Amendobobos",
    "Health": 1000,
    "Itens": [
      { "Nome": "Kokusen" },
      { "Nome": "ChuteDeFogo" },
      { "Nome": "ChuteCongelante"},
      { "Nome": "Rasteira" },
      { "Nome": "Susanoo" },
      { "Nome": "Rinnegan" },
      { "Nome": "Raio" }
    ],
    "Colors": {
      "Nome": { "Texto": [0, 0, 0], "Borda": [255, 255, 0] },
      "Patente": { "Texto": [0, 0, 0], "Borda": [255, 255, 0] },
      "Team": { "Texto": [0, 0, 0], "Borda": [255, 255, 0] }
    }
  },

  "825609349": {
    "Name": "Os Hashiras",
    "Health": 10000,
    "Itens": [
      { "Nome": "SlayerMark" },
      { "Nome": "ChuteDeFogo" },
      { "Nome": "Rasteira" },
      { "Nome": "SusanooEspada" },
      { "Nome": "CorteCircular" },
      { "Nome": "CorteDoSol" },
      { "Nome": "Raio" }
    ],
    "Colors": {
      "Nome": { "Texto": [0, 0, 0], "Borda": [255, 255, 255] },
      "Patente": { "Texto": [0, 0, 0], "Borda": [0, 0, 255] },
      "Team": { "Texto": [0, 0, 0], "Borda": [0, 0, 255] }
    }
  },

  "755862819": {
    "Name": "Anarquistas",
    "Health": 10000,
    "Itens": [
      { "Nome": "Kokusen" },
      { "Nome": "ChuteDeFogo" },
      { "Nome": "Rasteira" },
      { "Nome": "Raio" },
      { "Nome": "Susanoo Skeleton" },
      { "Nome": "Rinnegan" },
      { "Nome": "HakiDoRei" },
      { "Nome": "The Real Esfere" }
    ]
  },

  "33994083": {
    "Name": "The Sith Imperium",
    "Health": 1000,
    "Itens": [
      { "Nome": "Kokusen" },
      { "Nome": "ChuteDeFogo" },
      { "Nome": "Rasteira" },
      { "Nome": "Raio" },
      { "Nome": "Susanoo" },
      { "Nome": "Rinnegan" }
    ],
    "Colors": {
      "Nome": { "Texto": [255, 255, 255], "Borda": [0, 0, 0] },
      "Patente": { "Texto": [255, 255, 255], "Borda": [0, 0, 0] },
      "Team": { "Texto": [255, 255, 255], "Borda": [0, 0, 0] }
    }
  },

  "33345163": {
    "Name": "Akatsuki",
    "Health": 1000,
    "Itens": [
      { "Nome": "Kokusen" },
      { "Nome": "ChuteDeFogo" },
      { "Nome": "Rasteira" },
      { "Nome": "Raio" },
      { "Nome": "Susanoo" },
      { "Nome": "Rinnegan" }
    ],
    "Colors": {
      "Nome": { "Texto": [255, 0, 0], "Borda": [0, 0, 0] },
      "Patente": { "Texto": [255, 0, 0], "Borda": [0, 0, 0] },
      "Team": { "Texto": [255, 0, 0], "Borda": [0, 0, 0] }
    }
  },

  "35283892": {
    "Name": "World Governnament",
    "Health": 1000,
    "Itens": [
      { "Nome": "Kokusen" },
      { "Nome": "ChuteDeFogo" },
      { "Nome": "Rasteira" },
      { "Nome": "Raio" },
      { "Nome": "Susanoo" },
      { "Nome": "Rinnegan" },
      { "Nome": "Water Dragon" }
    ],
    "Colors": {
      "Nome": { "Texto": [0, 0, 0], "Borda": [124, 175, 172] },
      "Patente": { "Texto": [0, 0, 0], "Borda": [124, 175, 172] },
      "Team": { "Texto": [0, 0, 0], "Borda": [124, 175, 172] }
    }
  },

  "34271955": {
    "Name": "Syndicate Reapers",
    "Health": 10000,
    "Itens": [
      { "Nome": "CorteCircular" },
      { "Nome": "Raio" },
      { "Nome": "SlayerMark" },
      { "Nome": "Rasteira" },
      { "Nome": "Ceifar" },
      { "Nome": "Dismantle" },
      { "Nome": "ChuteDeFogo" },
      { "Nome": "SusanooEspada" },
      { "Nome": "Rinnegan" },
      { "Nome": "Colateral" },
      { "Nome": "Void Gate" },
      { "Nome": "Bang" }
    ]
  }
}
